passagemath_qepcad-10.6.43.dist-info/RECORD
passagemath_qepcad-10.6.43.dist-info/WHEEL
passagemath_qepcad-10.6.43.dist-info/top_level.txt
passagemath_qepcad-10.6.43.dist-info/METADATA
sage_wheels/bin/qepcad
sage_wheels/share/qepcad/qepcad.help
passagemath_qepcad/__init__.py
passagemath_qepcad/.dylibs/libreadline.8.2.dylib
sage/all__sagemath_qepcad.py
sage/libs/qepcad.cpython-310-darwin.so
sage/libs/all__sagemath_qepcad.py
sage/libs/qepcad.pyx
sage/interfaces/qepcad.py
sage/interfaces/all__sagemath_qepcad.py
